LICENSE
README.md
setup.py
Topsis_Abhinav_101903756/__init__.py
Topsis_Abhinav_101903756.egg-info/PKG-INFO
Topsis_Abhinav_101903756.egg-info/SOURCES.txt
Topsis_Abhinav_101903756.egg-info/dependency_links.txt
Topsis_Abhinav_101903756.egg-info/requires.txt
Topsis_Abhinav_101903756.egg-info/top_level.txt