Metadata-Version: 2.1
Name: Topsis-Abhinav-101903756
Version: 3.0
Summary: Topsis Calculation
Author: Abhinav Sinha
Author-email: sinha18abhinav@gmail.com
License: MIT
Keywords: Topsis,TopsisPackage
Platform: UNKNOWN
Classifier: Development Status :: 3 - Alpha
Classifier: Intended Audience :: Developers
Classifier: License :: OSI Approved :: MIT License
Classifier: Programming Language :: Python :: 3
Classifier: Programming Language :: Python :: 3.4
Classifier: Programming Language :: Python :: 3.5
Classifier: Programming Language :: Python :: 3.6
License-File: LICENSE
